awesomeTaskPy/__init__.py
awesomeTaskPy/context/__init__.py
awesomeTaskPy/context/context.py
awesomeTaskPy/context/event.py
awesomeTaskPy/context/systemEventRegister.py
awesomeTaskPy/log/__init__.py
awesomeTaskPy/log/loger.py
awesomeTaskPy/queue/__init__.py
awesomeTaskPy/queue/queue.py
awesomeTaskPy/task/__init__.py
awesomeTaskPy/task/baseTask.py
awesomeTaskPy/task/childrenTask.py
awesomeTaskPy-1.0.23.dist-info/LICENSE
awesomeTaskPy-1.0.23.dist-info/METADATA
awesomeTaskPy-1.0.23.dist-info/WHEEL
awesomeTaskPy-1.0.23.dist-info/top_level.txt
awesomeTaskPy-1.0.23.dist-info/RECORD
