Metadata-Version: 2.1
Name: awesomeTaskPy
Version: 1.0.23
Summary: 分布式执行任务
Home-page: https://gitee.com/jjawesomejj/awesome-task-py
Author: jjawesome
Author-email: 1293777844@qq.com
Maintainer: jjawesome
Maintainer-email: 1293777844@qq.com
License: BSD License
Platform: all
Classifier: Development Status :: 4 - Beta
Classifier: Operating System :: OS Independent
Classifier: Intended Audience :: Developers
Classifier: License :: OSI Approved :: BSD License
Classifier: Programming Language :: Python
Classifier: Programming Language :: Python :: Implementation
Classifier: Programming Language :: Python :: 2
Classifier: Programming Language :: Python :: 2.7
Classifier: Programming Language :: Python :: 3
Classifier: Programming Language :: Python :: 3.4
Classifier: Programming Language :: Python :: 3.5
Classifier: Programming Language :: Python :: 3.6
Classifier: Topic :: Software Development :: Libraries
